bear_to_paper/__init__.py
bear_to_paper/cmdline.py
bear_to_paper/migrator.py
bear_to_paper/reader.py
bear_to_paper-0.1.1.dist-info/METADATA
bear_to_paper-0.1.1.dist-info/RECORD
bear_to_paper-0.1.1.dist-info/WHEEL
bear_to_paper-0.1.1.dist-info/entry_points.txt
bear_to_paper-0.1.1.dist-info/top_level.txt
