Metadata-Version: 2.1
Name: bear-to-paper
Version: 0.1.1
Summary: Migrate your Bear notes to Paper.
Home-page: https://github.com/coddingtonbear/bear-to-paper
Author: Adam Coddington
Author-email: me@adamcoddington.net
License: UNKNOWN
Platform: UNKNOWN
Classifier: License :: OSI Approved :: MIT License
Classifier: Operating System :: OS Independent
Classifier: Programming Language :: Python :: 3
